<?xml version="1.0"?>
<!DOCTYPE hibernate-mapping PUBLIC "-//Hibernate/Hibernate Mapping DTD 3.0//EN"
"http://www.hibernate.org/dtd/hibernate-mapping-3.0.dtd">
<!-- Generated 29-nov-2016 15:59:42 by Hibernate Tools 4.3.1 -->
<hibernate-mapping>
    <class name="Entities.Users" table="users" catalog="thewallet" optimistic-lock="version">
        <id name="idUser" type="java.lang.Integer">
            <column name="idUser" />
            <generator class="identity" />
        </id>
        <property name="username" type="string">
            <column name="username" length="16" not-null="true" />
        </property>
        <property name="password" type="string">
            <column name="password" length="16" not-null="true" />
        </property>
        <set name="transactionses" table="transactions" inverse="true" lazy="true" fetch="select">
            <key>
                <column name="idUser" not-null="true" />
            </key>
            <one-to-many class="Entities.Transactions" />
        </set>
    </class>
</hibernate-mapping>
